scr/discordsimplimised/__init_.py
scr/discordsimplimised/discordsimplimised.py
scr/discordsimplimised/example.py
discordsimplimised-1.3.dist-info/LICENSE.txt
discordsimplimised-1.3.dist-info/METADATA
discordsimplimised-1.3.dist-info/WHEEL
discordsimplimised-1.3.dist-info/top_level.txt
discordsimplimised-1.3.dist-info/RECORD
