Metadata-Version: 2.1
Name: discordsimplimised
Version: 1.3
Summary: discordsimplimised is a made to make making a discord bot easier to make
Author-email: Sheep26 <crabeykiller@gmail.com>
Project-URL: Homepage, https://github.com/Sheep26/discord-simplimised
Project-URL: Bug Tracker, https://github.com/Sheep26/discord-simplimised/issues
Classifier: Programming Language :: Python :: 3
Classifier: License :: OSI Approved :: MIT License
Classifier: Operating System :: OS Independent
Requires-Python: >=3.6
License-File: LICENSE.txt
Requires-Dist: discord
Requires-Dist: discord.py
